LICENSE
MANIFEST.in
README.rst
setup.py
simplewrap/__init__.py
simplewrap/c_matlab.py
simplewrap/c_python.py
simplewrap/c_python2.py
simplewrap/exceptions.py
simplewrap.egg-info/PKG-INFO
simplewrap.egg-info/SOURCES.txt
simplewrap.egg-info/dependency_links.txt
simplewrap.egg-info/requires.txt
simplewrap.egg-info/top_level.txt
simplewrap/examples/__init__.py
simplewrap/tests/__init__.py
simplewrap/tests/test_all.py
simplewrap/tests/test_matrices_c.c
simplewrap/tests/test_simplewrap_c.c